accessible_django/__init__.py
accessible_django/apps.py
accessible_django/checks/__init__.py
accessible_django/checks/img.py
accessible_django/utils/__init__.py
accessible_django/utils/get_template_dirs.py
accessible_django/validators/__init__.py
accessible_django/validators/base.py
accessible_django/validators/img_tag.py
tests/__init__.py
tests/settings.py
tests/test_img.py
accessible_django-1.0.0.dist-info/LICENSE
accessible_django-1.0.0.dist-info/METADATA
accessible_django-1.0.0.dist-info/WHEEL
accessible_django-1.0.0.dist-info/top_level.txt
accessible_django-1.0.0.dist-info/RECORD
