Metadata-Version: 2.1
Name: accessible-django
Version: 1.0.0
Summary: A Django package for accessibility checks during development.
Author: Johanan Oppong Amoateng
Author-email: johananoppongamoateng2001@gmail.com
License: MIT
Classifier: Programming Language :: Python :: 3.10
Classifier: Framework :: Django
Classifier: License :: OSI Approved :: MIT License
Classifier: Operating System :: OS Independent
Classifier: Programming Language :: Python
Classifier: Programming Language :: Python :: 3
Classifier: Programming Language :: Python :: 3.10
Classifier: Programming Language :: Python :: 3.11
Classifier: Framework :: Django
Classifier: Framework :: Django :: 5
Classifier: Topic :: Software Development :: Libraries :: Python Modules
Classifier: Topic :: Software Development :: Libraries
Requires-Python: >=3.10
License-File: LICENSE
Requires-Dist: beautifulsoup4>=4.9.3
Requires-Dist: Django>=5.1.2
Requires-Dist: mkdocs==1.6.1
Requires-Dist: setuptools==75.6.0
